Changelog.rst
MANIFEST.in
README.rst
VERSION.txt
setup.cfg
setup.py
conf/__init__.py
conf/__init__.pyc
conf/kansha.cfg
data/__init__.py
data/assets/EMPTY_DIR
data/captcha/ashcanbb_bold.ttf
data/captcha/captcha-bg.png
data/locale/messages.pot
data/locale/fr/LC_MESSAGES/messages.mo
data/locale/fr/LC_MESSAGES/messages.po
data/locale/ja/LC_MESSAGES/messages.mo
data/locale/ja/LC_MESSAGES/messages.po
data/locale/tr/LC_MESSAGES/messages.mo
data/locale/tr/LC_MESSAGES/messages.po
data/logs/EMPTY_DIR
kansha/__init__.py
kansha/events.py
kansha/exceptions.py
kansha/helpers.py
kansha/menu.py
kansha/models.py
kansha/notifications.py
kansha/pickle.py
kansha/populate.py
kansha/security.py
kansha/validator.py
kansha.egg-info/PKG-INFO
kansha.egg-info/SOURCES.txt
kansha.egg-info/dependency_links.txt
kansha.egg-info/entry_points.txt
kansha.egg-info/not-zip-safe
kansha.egg-info/requires.txt
kansha.egg-info/top_level.txt
kansha/alembic/__init__.py
kansha/alembic/__init__.pyc
kansha/alembic/admin.py
kansha/alembic/env.py
kansha/alembic/script.py.mako
kansha/alembic/versions/1b6fbaffad32_add_notify_value.py
kansha/alembic/versions/1bd634091036_add_display_week_numbers.py
kansha/alembic/versions/24be36b8c67_new_asset_path_to_assets.py
kansha/alembic/versions/25739bc150b9_membership.py
kansha/alembic/versions/2b0edcfa57b4_add_templates.py
kansha/alembic/versions/2c0a3788227_rm_display_week_numbers.py
kansha/alembic/versions/361f9cbae3fc_rename_board_archive.py
kansha/alembic/versions/36d972f11e3e_board_background.py
kansha/alembic/versions/443501b69d16_weights_are_numbers.py
kansha/alembic/versions/4fb34b202c5f_last_login_stamp.py
kansha/alembic/versions/537fa16b46e7_add_due_date_to_card.py
kansha/alembic/versions/55f89221fc55_email_index.py
kansha/alembic/versions/5791b368ac26_new_background_positions.py
kansha/alembic/versions/6cb3c668d65_add_column_archive_flag.py
kansha/alembic/versions/b740362087_adding_max_cards.py
kansha/alembic/versions/d0e88000d3f_add_versioning.py
kansha/alembic/versions/f058ce7ee0c_data_in_extensions.py
kansha/app/__init__.py
kansha/app/comp.py
kansha/app/urls.py
kansha/app/view.py
kansha/authentication/__init__.py
kansha/authentication/login.py
