Metadata-Version: 1.0
Name: kansha
Version: 2.0.4
Summary: Manage and share collaborative pinboards on the web.
Home-page: UNKNOWN
Author: Net-ng
Author-email: contact@net-ng.com
License: BSD
Platform: UNKNOWN
